jaegertrace/__init__.py
jaegertrace/conf.py
jaegertrace/httpclient.py
jaegertrace/initial_tracer.py
jaegertrace/middleware.py
jaegertrace/request_context.py
tests/__init__.py
tests/test_inboud.py
jaeger_django-1.0.2.dist-info/LICENSE
jaeger_django-1.0.2.dist-info/METADATA
jaeger_django-1.0.2.dist-info/WHEEL
jaeger_django-1.0.2.dist-info/top_level.txt
jaeger_django-1.0.2.dist-info/RECORD
