Metadata-Version: 2.1
Name: jaeger-django
Version: 1.0.2
Summary: service tracing using jaeger in django project
Home-page: UNKNOWN
Author: lxkaka
Author-email: linxiaoking@gamil.com
License: Apache License 2.0
Keywords: jaeger,tracing,django
Platform: UNKNOWN
Classifier: Intended Audience :: Developers
Classifier: License :: OSI Approved :: Apache Software License
Classifier: Natural Language :: English
Classifier: Programming Language :: Python :: 3.6
Requires-Dist: jaeger-client (>=3.11.0)
Requires-Dist: django (>=1.8)
Requires-Dist: requests (>=2.19.1)
